survive996/__init__.py
survive996/xib/__init__.py
survive996/xib/meituan/__init__.py
survive996/xib/meituan/accountant.py
survive996/xib/meituan/datareader.py
survive996/xib/meituan/metadata/__init__.py
survive996/xib/meituan/metadata/table.py
survive996/xib/meituan/metadata/trade.py
survive996test/__init__.py
survive996test/xib/__init__.py
survive996test/xib/datareadertest.py
survive996-0.0.5.dist-info/LICENSE
survive996-0.0.5.dist-info/METADATA
survive996-0.0.5.dist-info/WHEEL
survive996-0.0.5.dist-info/top_level.txt
survive996-0.0.5.dist-info/RECORD
