Metadata-Version: 2.1
Name: survive996
Version: 0.0.5
Summary: A lib for daily work
Home-page: https://github.com/23spongebob/survive996
Author: spongebob
Author-email: author@example.com
License: UNKNOWN
Platform: UNKNOWN
Classifier: Programming Language :: Python :: 3
Classifier: License :: OSI Approved :: MIT License
Classifier: Operating System :: OS Independent
Requires-Python: >=3.5
